edw.seleniumtesting-1.1-py3.6-nspkg.pth
edw/seleniumtesting/__init__.py
edw/seleniumtesting/common.py
edw/seleniumtesting/main.py
edw/seleniumtesting/sample.py
edw/seleniumtesting/util.py
edw.seleniumtesting-1.1.dist-info/METADATA
edw.seleniumtesting-1.1.dist-info/RECORD
edw.seleniumtesting-1.1.dist-info/WHEEL
edw.seleniumtesting-1.1.dist-info/entry_points.txt
edw.seleniumtesting-1.1.dist-info/namespace_packages.txt
edw.seleniumtesting-1.1.dist-info/top_level.txt
