Metadata-Version: 2.1
Name: edw.seleniumtesting
Version: 1.1
Summary: Selenium testing metapackage
Home-page: https://pypi.python.org/pypi/edw.seleniumtesting
Author: David Bătrânu
Author-email: david.batranu@eaudeweb.ro
License: GPL version 2
Keywords: Python Plone
Platform: UNKNOWN
Classifier: Programming Language :: Python
Classifier: Programming Language :: Python :: 3.5
Classifier: Operating System :: OS Independent
Classifier: License :: OSI Approved :: GNU General Public License v2 (GPLv2)
Requires-Dist: setuptools
Requires-Dist: selenium (>=3.0.2)
